flask_sqlalchemy/__init__.py
flask_sqlalchemy/cli.py
flask_sqlalchemy/extension.py
flask_sqlalchemy/model.py
flask_sqlalchemy/pagination.py
flask_sqlalchemy/py.typed
flask_sqlalchemy/query.py
flask_sqlalchemy/record_queries.py
flask_sqlalchemy/session.py
flask_sqlalchemy/table.py
flask_sqlalchemy/track_modifications.py
Flask_SQLAlchemy-3.0.3.dist-info/WHEEL
Flask_SQLAlchemy-3.0.3.dist-info/METADATA
Flask_SQLAlchemy-3.0.3.dist-info/licenses/LICENSE.rst
Flask_SQLAlchemy-3.0.3.dist-info/RECORD
