Metadata-Version: 2.1
Name: Flask-SQLAlchemy
Version: 3.0.3
Summary: Add SQLAlchemy support to your Flask application.
License: BSD-3-Clause
Author-email: Armin Ronacher <armin.ronacher@active-4.com>
Maintainer-email: Pallets <contact@palletsprojects.com>
Requires-Python: >=3.7
Classifier: Development Status :: 5 - Production/Stable
Classifier: Environment :: Web Environment
Classifier: Intended Audience :: Developers
Classifier: License :: OSI Approved :: BSD License
Classifier: Operating System :: OS Independent
Classifier: Programming Language :: Python
Classifier: Topic :: Internet :: WWW/HTTP :: Dynamic Content
Project-URL: Changes, https://flask-sqlalchemy.palletsprojects.com/changes/
Project-URL: Chat, https://discord.gg/pallets
Project-URL: Documentation, https://flask-sqlalchemy.palletsprojects.com/
Project-URL: Donate, https://palletsprojects.com/donate
Project-URL: Issue Tracker, https://github.com/pallets-eco/flask-sqlalchemy/issues/
Project-URL: Source Code, https://github.com/pallets-eco/flask-sqlalchemy/
Project-URL: Twitter, https://twitter.com/PalletsTeam
